[
  {
    "id": 1650700992714,
    "name": "27054466",
    "size": "20",
    "colorButtons": "#eab18d",
    "font": "Roboto",
    "userId": 1648546148600
  },
  {
    "id": 1650701792577,
    "name": "57344604",
    "size": 24,
    "colorButtons": "#1e98d7",
    "font": "Luciole",
    "userId": 1648546148600
  },
  {
    "id": 1650705334559,
    "name": "17497372",
    "size": 24,
    "colorButtons": "#5B793D",
    "font": "Luciole",
    "userId": 1
  },
  {
    "id": 1650705338637,
    "name": "83927548",
    "size": 24,
    "colorButtons": "#696969",
    "font": "Luciole",
    "userId": 1
  },
  {
    "id": 1650720237505,
    "name": "10064498",
    "size": "32",
    "colorButtons": "#696969",
    "font": "Roboto",
    "horizontalEccentricity": "60%",
    "verticalEccentricity": "60%",
    "userId": 3
  }
]